ShakenCBLattice/CheckerboardLattice.py
ShakenCBLattice/ExtendedBasisLattice.py
ShakenCBLattice/TrotterLattice.py
ShakenCBLattice/__init__.py
ShakenCBLattice-0.1.0.dist-info/METADATA
ShakenCBLattice-0.1.0.dist-info/WHEEL
ShakenCBLattice-0.1.0.dist-info/top_level.txt
ShakenCBLattice-0.1.0.dist-info/RECORD
