Metadata-Version: 2.1
Name: ShakenCBLattice
Version: 0.1.0
Summary: Package used to perform band structure caluclations on periodically driven Checkerboard optical lattice
Home-page: UNKNOWN
Author: James Maslek
Author-email: jmaslek11@gmail.com
License: UNKNOWN
Platform: UNKNOWN
